{"_id":"1120775358129819649","created_at":1556048643,"lang":"es","retweeted_status":{"_id":"1120751249853493249","user":{"followers_count":419,"friends_count":729,"id_str":"3053006624","lang":"es","screen_name":"ElOtroPuchi","statuses_count":12966}},"text":"RT @ElOtroPuchi: Jajajaja. Pero @gabrielrufian Retuiteas para señalarme? Jajajaja Eres muy tonto Me suda el nabo que lo hagas Vendrán tus l…","user":{"followers_count":108,"friends_count":229,"id_str":"143601881","lang":"es","screen_name":"horus230480","statuses_count":719}}
{"_id":"1120775385740922880","created_at":1556048649,"lang":"ca","retweeted_status":{"_id":"1120712684754866176","user":{"followers_count":264499,"friends_count":112,"id_str":"145670919","lang":"ca","screen_name":"govern","statuses_count":50002}},"text":"RT @govern: 📷 El #president @QuimTorraiPla ha col·laborat amb la campanya “Roses contra l'oblit”, organitzada per l'associació Amics de la…","user":{"followers_count":55,"friends_count":59,"id_str":"977276221653422082","lang":"ca","screen_name":"martamu4","statuses_count":20689}}
{"_id":"1120775597813268482","created_at":1556048700,"lang":"und","text":"🤣","user":{"followers_count":50,"friends_count":600,"id_str":"54081492","lang":"en","screen_name":"RustySprouts","statuses_count":31146}}
{"_id":"1120775605509918720","created_at":1556048702,"lang":"es","retweeted_status":{"_id":"1120768601538080769","user":{"followers_count":69,"friends_count":25,"id_str":"593866123","lang":"es","screen_name":"durisimo08","statuses_count":6755}},"text":"RT @durisimo08: @Pablo_Iglesias_ Sin medias tintas\n💙 @populares @pablocasado_ \n🌹@PSOE @sanchezcastejon\n🍊 @CiudadanosCs @Albert_Rivera\n💜 @ah…","user":{"followers_count":0,"friends_count":0,"id_str":"1120768088276897793","lang":"en","screen_name":"Cesteros61","statuses_count":168}}
{"_id":"1120775645968125953","created_at":1556048711,"lang":"es","retweeted_status":{"_id":"1120773149648465925","user":{"followers_count":178,"friends_count":249,"id_str":"3291985936","lang":"en","screen_name":"sacan02","statuses_count":6887}},"text":"RT @sacan02: @Lordcrow11 @RobinDeEspacio Cuidado con lo que llega por correo. Está papeleta es nula por el 10 que va en VOX. https://t.co/7…","user":{"followers_count":5184,"friends_count":5188,"id_str":"877894890218246144","lang":"es","screen_name":"RobinDeEspacio","statuses_count":37753}}
{"_id":"1120775762506911746","created_at":1556048739,"lang":"es","retweeted_status":{"_id":"1120770996817018880","user":{"followers_count":165,"friends_count":125,"id_str":"4619297542","lang":"es","screen_name":"borealas","statuses_count":10906}},"text":"RT @borealas: Vox no está en el debate pero Ferreras nos lo hace presente. \n\n#ElDebateDecisivo\n#DebateDecisivoARV","user":{"followers_count":1303,"friends_count":581,"id_str":"582532871","lang":"es","screen_name":"SLSeco","statuses_count":21582}}
{"_id":"1120776016664903681","created_at":1556048800,"lang":"es","retweeted_status":{"_id":"1120702204518838283","user":{"followers_count":63,"friends_count":296,"id_str":"941070234210971649","lang":"es","screen_name":"RegiJoseRamonS","statuses_count":2634}},"text":"RT @RegiJoseRamonS: @Rafa_eltorete @Cristin83590981 Rafael, el señor Rivera está así porque la Moción le dejó descolocado, su estrategia er…","user":{"followers_count":4466,"friends_count":4319,"id_str":"2412494393","lang":"es","screen_name":"JulioAl18175505","statuses_count":302530}}
{"_id":"1120776079134871552","created_at":1556048814,"lang":"es","retweeted_status":{"_id":"1120712327551246336","user":{"followers_count":1888,"friends_count":3151,"id_str":"538236196","lang":"es","screen_name":"Dorisday58","statuses_count":73922}},"text":"RT @Dorisday58: ¿Por que se DISCRIMINA a las mujeres que han tenido 1 hijo,como si no hubieran hecho ellas también un gran esfuerzo (muchas…","user":{"followers_count":1888,"friends_count":3151,"id_str":"538236196","lang":"es","screen_name":"Dorisday58","statuses_count":73923}}
{"_id":"1120776217966403584","created_at":1556048848,"lang":"es","retweeted_status":{"_id":"1120762758205706242","user":{"followers_count":494811,"friends_count":1259,"id_str":"552561770","lang":"es","screen_name":"InesArrimadas","statuses_count":3697}},"text":"RT @InesArrimadas: Gracias a Cs el IVA cultural pasó del 21% al 10% y ahora apostamos por 👇🏼\n✅ IVA superreducido para prensa digital y libr…","user":{"followers_count":176,"friends_count":392,"id_str":"282137110","lang":"es","screen_name":"nistalfeli","statuses_count":1968}}
{"_id":"1120776250296078336","created_at":1556048855,"lang":"es","retweeted_status":{"_id":"1120664104950222849","user":{"followers_count":164,"friends_count":180,"id_str":"2974740953","lang":"es","screen_name":"Jorge_Sagita63","statuses_count":11099}},"text":"RT @Jorge_Sagita63: @sanchezcastejon Gracias por saludar a España y no incluir a Catalunya. 😂😂😂😂\nLo sabemos: somos un país diferente.","user":{"followers_count":3110,"friends_count":1637,"id_str":"252765640","lang":"ca","screen_name":"enjordinavarro","statuses_count":64706}}
{"_id":"1120776264690880512","created_at":1556048859,"lang":"es","retweeted_status":{"_id":"1120428022472040450","user":{"followers_count":6895559,"friends_count":754,"id_str":"7996082","lang":"es","screen_name":"el_pais","statuses_count":477041}},"text":"RT @el_pais: El verificador de EL PAÍS en #ELDEBATEenRTVE  | Es falso que Zapatero dejara quebrado el sistema de Seguridad Social, como ha…","user":{"followers_count":1259,"friends_count":1183,"id_str":"509071336","lang":"es","screen_name":"carmen_maron","statuses_count":9555}}
{"_id":"1120776551241539589","created_at":1556048927,"lang":"es","text":"PRD solicita a la Junta Central Electoral supervisar reunión de la comisión política https://t.co/181nxACLq8 https://t.co/EJ20mdeik5","user":{"followers_count":838,"friends_count":430,"id_str":"2903268286","lang":"es","screen_name":"albertpuello809","statuses_count":15190}}
{"_id":"1120776595214602248","created_at":1556048937,"lang":"es","retweeted_status":{"_id":"1120324632739971072","user":{"followers_count":23366,"friends_count":994,"id_str":"179304336","lang":"es","screen_name":"Elba_Celo","statuses_count":69146}},"text":"RT @Elba_Celo: Lo siguiente de Vox será defender el derecho del violador a violarnos. https://t.co/aILqza11l0","user":{"followers_count":350,"friends_count":960,"id_str":"69116986","lang":"en","screen_name":"sinzapati","statuses_count":28050}}
{"_id":"1120776602890190848","created_at":1556048939,"lang":"es","retweeted_status":{"_id":"1120754082933878786","user":{"followers_count":123,"friends_count":374,"id_str":"703743296","lang":"es","screen_name":"miap73","statuses_count":2824}},"text":"RT @miap73: Jusapol apolítico, equiparación real, mismo trabajo = mismo sueldo\n#EquiparacionYa \n#ElDebateDecisivo \n#ILPJusapol\n@jusapol \n@P…","user":{"followers_count":262,"friends_count":623,"id_str":"831788208274939905","lang":"es","screen_name":"SantrixCB","statuses_count":7454}}
{"_id":"1120776655897792512","created_at":1556048952,"lang":"es","retweeted_status":{"_id":"1120440515265204227","user":{"followers_count":74,"friends_count":193,"id_str":"1045019438049906688","lang":"es","screen_name":"gabriel_eg93","statuses_count":772}},"text":"RT @gabriel_eg93: Vamos a petarle la cuenta a @Albert_Rivera con esta foto. #ELDEBATEenRTVE https://t.co/vyfLIEiaRD","user":{"followers_count":682,"friends_count":1569,"id_str":"1249396134","lang":"ca","screen_name":"amarantagibert","statuses_count":11897}}
{"_id":"1120776665813192704","created_at":1556048954,"lang":"und","text":"👉🏼👉🏼👉🏼","user":{"followers_count":1113,"friends_count":949,"id_str":"150761443","lang":"es","screen_name":"AngieCapel","statuses_count":9470}}
{"_id":"1120776756821204996","created_at":1556048976,"lang":"es","retweeted_status":{"_id":"1120423156676689922","user":{"followers_count":108973,"friends_count":1820,"id_str":"157809480","lang":"es","screen_name":"Ruiz_Noticias","statuses_count":3116}},"text":"RT @Ruiz_Noticias: PABLO IGLESIAS PLANTEA UNA REBAJA DEL IVA DEL 10 AL 4% PARA LOS PRODUCTOS BÁSICOS: La rebaja se aplicaría para: \n— Energ…","user":{"followers_count":85,"friends_count":201,"id_str":"2503858621","lang":"es","screen_name":"sigonsig","statuses_count":17404}}
{"_id":"1120776920872964097","created_at":1556049015,"lang":"es","retweeted_status":{"_id":"1120764989244104705","user":{"followers_count":1809,"friends_count":1114,"id_str":"901088917767823361","lang":"es","screen_name":"jusapolcoruna","statuses_count":7717}},"text":"RT @jusapolcoruna: 👉🏻 Hoy tenemos el #DebateDecisivo de las elecciones del #28A  \n\n✔Queremos compromisos concretos con la #EquiparacionYa…","user":{"followers_count":58,"friends_count":399,"id_str":"2770811221","lang":"es","screen_name":"netmanu100373","statuses_count":9656}}
{"_id":"1120776948156895232","created_at":1556049022,"lang":"und","text":"@Vox_Bezana","user":{"followers_count":8,"friends_count":9,"id_str":"1108128199626670080","lang":"en","screen_name":"Isidoro18929874","statuses_count":5}}
{"_id":"1120777037512355840","created_at":1556049043,"lang":"es","retweeted_status":{"_id":"1120345339851153411","user":{"followers_count":14943,"friends_count":2680,"id_str":"304342684","lang":"es","screen_name":"AmparoRubiales","statuses_count":150088}},"text":"RT @AmparoRubiales: El Psoe valenciano, con el tirón de Àbalos, a punto de obtener su mejor resultado electoral en 30 años con 12 diputados…","user":{"followers_count":3825,"friends_count":4994,"id_str":"636268171","lang":"es","screen_name":"nusagatero","statuses_count":312557}}
{"_id":"1120777109948051456","created_at":1556049060,"lang":"und","place":{"bounding_box":{"coordinates":[[[-4.361575,41.093151],[-4.361575,41.19641],[-4.223224,41.19641],[-4.223224,41.093151]]],"type":"Polygon"},"country_code":"ES","id":"841c7d90e0407df5","name":"Carbonero el Mayor","place_type":"city"},"text":"😂😂😂","user":{"followers_count":210,"friends_count":469,"id_str":"121738415","lang":"es","screen_name":"GrdilloSofia","statuses_count":2474}}
{"_id":"1120777135680045058","created_at":1556049066,"lang":"es","retweeted_status":{"_id":"1120626195190767619","user":{"followers_count":102582,"friends_count":1908,"id_str":"387664374","lang":"es","screen_name":"PabloHasel","statuses_count":13142}},"text":"RT @PabloHasel: El alcalde del PSOE del pueblo donde se simuló fusilar a Puigdemont puede justificarlo pero como digas que con dinero públi…","user":{"followers_count":181,"friends_count":156,"id_str":"277459142","lang":"ca","screen_name":"pitusihara","statuses_count":50656}}
{"_id":"1120777164058714113","created_at":1556049073,"lang":"und","retweeted_status":{"_id":"1120776006879580166","user":{"followers_count":21,"friends_count":29,"id_str":"999933706369413120","lang":"es","screen_name":"hernidelicias","statuses_count":3276}},"text":"RT @hernidelicias: #EquiparacionYa\n#ElDebateDecisivo\n#ILPJusapol\n@jusapol\n@PSOE\n@populares\n@ahorapodemos\n@CiudadanosCs\n@vox_es\n@europapress…","user":{"followers_count":2951,"friends_count":2839,"id_str":"744171338978463744","lang":"es","screen_name":"tizona_colada","statuses_count":110627}}
{"_id":"1120777204139474944","created_at":1556049083,"lang":"und","retweeted_status":{"_id":"1120751941175398408","user":{"followers_count":117,"friends_count":103,"id_str":"237159677","lang":"es","screen_name":"Jota_Quijada","statuses_count":2710}},"text":"RT @Jota_Quijada: @A3Noticias @atresmediacom @_anapastor_ @VicenteVallesTV @MomentsES #EquiparacionYa\n#ELDEBATEenRTVE\n@jusapol\n@sanchezcast…","user":{"followers_count":4,"friends_count":24,"id_str":"4383722608","lang":"es","screen_name":"patrygine7","statuses_count":17}}
{"_id":"1120777535867052038","created_at":1556049162,"lang":"es","retweeted_status":{"_id":"1120769068414504960","user":{"followers_count":1797,"friends_count":306,"id_str":"2865259719","lang":"es","screen_name":"AlvareJoaquin","statuses_count":4989}},"text":"RT @AlvareJoaquin: @ahorapodemos @Pablo_Iglesias_ Grande Pablo!! https://t.co/Hx4DEs91nU","user":{"followers_count":413,"friends_count":387,"id_str":"432279478","lang":"es","screen_name":"juanjopeseto","statuses_count":26123}}
{"_id":"1120777551402680320","created_at":1556049165,"lang":"es","text":"RT ahorapodemos: 🚕 Pablo_Iglesias_ llega al debate electoral en transporte público, en taxi.\n\n #DebateAtresmedia… https://t.co/3XjgHt7csD","user":{"followers_count":3136,"friends_count":2744,"id_str":"317007370","lang":"es","screen_name":"taxi_tweet","statuses_count":30987}}
{"_id":"1120777671707963393","created_at":1556049194,"lang":"es","retweeted_status":{"_id":"1120412675182333955","user":{"followers_count":326687,"friends_count":1329,"id_str":"268470229","lang":"es","screen_name":"jesusmarana","statuses_count":41777}},"text":"RT @jesusmarana: “Una mujer violada no tiene que abortar”, sostiene una candidata de #Vox (y dice su partido que se ha “sacado de contexto”…","user":{"followers_count":6278,"friends_count":5423,"id_str":"3676608376","lang":"es","screen_name":"igualdadpsoem","statuses_count":18009}}
{"_id":"1120777725193740293","created_at":1556049207,"lang":"es","retweeted_status":{"_id":"1120776785539551238","user":{"followers_count":1240,"friends_count":1695,"id_str":"1282367214","lang":"es","screen_name":"mmartinez0064","statuses_count":27928}},"text":"RT @mmartinez0064: @ivanedlm @guardiacivil @vox_es  NO OLVIDEN DIGNIFICAR A FFCCSE \n#EquiparacionYa\n\n#ElDebateDecisivo\n#ILPJusapol\n@jusapol…","user":{"followers_count":252,"friends_count":162,"id_str":"818967931619000320","lang":"es","screen_name":"RMRlangostino","statuses_count":11750}}
{"_id":"1120777740687478786","created_at":1556049211,"lang":"es","retweeted_status":{"_id":"1120757993283493889","user":{"followers_count":1387,"friends_count":417,"id_str":"944154739167637504","lang":"es","screen_name":"jusapoltoledo","statuses_count":25563}},"text":"RT @jusapoltoledo: @A3Noticias @atresmediacom @_anapastor_ @VicenteVallesTV @MomentsES Quien de ellos se compromete a romper #30AñosDeInjus…","user":{"followers_count":1307,"friends_count":834,"id_str":"892294078326607874","lang":"es","screen_name":"Francis35247769","statuses_count":137412}}
{"_id":"1120777850041376773","created_at":1556049237,"lang":"es","retweeted_status":{"_id":"1120662490923376643","user":{"followers_count":7463,"friends_count":6337,"id_str":"550116886","lang":"es","screen_name":"MariaMonteroTFE","statuses_count":39888}},"text":"RT @MariaMonteroTFE: #laventanaindiscreta con @pedrinmatita El #DebateRTVE dejó a los candidatos en caída libre sobre la #EquiparacionYa pq…","user":{"followers_count":525,"friends_count":1162,"id_str":"798767220","lang":"es","screen_name":"miguelparadel","statuses_count":9293}}
{"_id":"1120777929930215425","created_at":1556049256,"lang":"es","retweeted_status":{"_id":"1120758340529922049","user":{"followers_count":25351,"friends_count":5945,"id_str":"124746336","lang":"es","screen_name":"CasoAislado_Es","statuses_count":6839}},"text":"RT @CasoAislado_Es: Ahora mismo en Las Rozas. Más de 5.000 españoles han llenado la Plaza de Toros de la localidad madrileña para asistir a…","user":{"followers_count":734,"friends_count":320,"id_str":"1162838845","lang":"es","screen_name":"rosapitufaC","statuses_count":114200}}
{"_id":"1120778196054675456","created_at":1556049319,"lang":"es","retweeted_status":{"_id":"1120759426774859781","user":{"followers_count":2380,"friends_count":1995,"id_str":"199645644","lang":"es","screen_name":"neviska","statuses_count":35585}},"text":"RT @neviska: Dijimos que @jusapol no se iba a rendir A ESTO NOS REFERIMOS. BRAVO VALIENTES. \n#EquiparacionYa\n#ElDebateDecisivo\n#ILPJusapol…","user":{"followers_count":3255,"friends_count":2694,"id_str":"900430680806608961","lang":"es","screen_name":"jusapolceuta","statuses_count":12478}}
{"_id":"1120778510296129538","created_at":1556049394,"lang":"es","retweeted_status":{"_id":"1120641261336236032","user":{"followers_count":7850,"friends_count":7744,"id_str":"127306615","lang":"es","screen_name":"madrid13nadamas","statuses_count":18743}},"text":"RT @madrid13nadamas: Deseando que llegue el debate para ver el modelo que lleva @Pablo_Iglesias_ . ¿Será aún más cochambroso que el de ayer…","user":{"followers_count":230,"friends_count":275,"id_str":"978377302286401537","lang":"es","screen_name":"mariace1307","statuses_count":9821}}
{"_id":"1120778554185322501","created_at":1556049405,"lang":"pt","retweeted_status":{"_id":"1120715843623583744","user":{"followers_count":1994,"friends_count":355,"id_str":"181609759","lang":"es","screen_name":"Cerdido_","statuses_count":46036}},"text":"RT @Cerdido_: Vota a VOX. https://t.co/OjoFli1Oam","user":{"followers_count":116,"friends_count":136,"id_str":"553933434","lang":"es","screen_name":"Claudi_Fatjo","statuses_count":10894}}
{"_id":"1120778648481669120","created_at":1556049427,"lang":"es","retweeted_status":{"_id":"1120410928791662592","user":{"followers_count":19725,"friends_count":16212,"id_str":"139748229","lang":"es","screen_name":"PatFBermejo","statuses_count":98172}},"text":"RT @PatFBermejo: ¡Ojo! \n1) @pablocasado_ , se abre él la puerta y sale. \n2) @Albert_Rivera se abre él la puerta y sale. \n3) @Pablo_Iglesias…","user":{"followers_count":136,"friends_count":425,"id_str":"935247090745212928","lang":"es","screen_name":"omus1969","statuses_count":9560}}
{"_id":"1120778743633600512","created_at":1556049450,"lang":"es","text":"@daniCanutillo @KopaLove_ @ElBioLoco @Barbijaputa @PartidoPACMA Un feto no es un ser que siente hasta pasados los t… https://t.co/u33n0j06ZR","user":{"followers_count":129,"friends_count":242,"id_str":"573906449","lang":"es","screen_name":"ecosdeti_","statuses_count":7222}}
{"_id":"1120778753758650369","created_at":1556049452,"lang":"es","retweeted_status":{"_id":"1120426703023636483","user":{"followers_count":106880,"friends_count":303,"id_str":"3018165370","lang":"es","screen_name":"rosadiezglez","statuses_count":21566}},"text":"RT @rosadiezglez: Dice Sánchez en #ELDEBATEenRTVE que le preocupa ‘la igualdad de género’. Más le valdría defender la igualdad de todos los…","user":{"followers_count":92,"friends_count":324,"id_str":"446244361","lang":"es","screen_name":"Salamiparatodas","statuses_count":4767}}
{"_id":"1120778762327556098","created_at":1556049454,"lang":"es","retweeted_status":{"_id":"1120758898061971457","user":{"followers_count":109617,"friends_count":4171,"id_str":"715579207","lang":"es","screen_name":"GobernoAlem","statuses_count":14055}},"text":"RT @GobernoAlem: Iglesias llega en Taxi al #DebateAtresmedia. Pudiendo llegar en un Lexus de 160.000€. Ya le vale.","user":{"followers_count":742,"friends_count":1576,"id_str":"2909725343","lang":"es","screen_name":"PortPartes","statuses_count":192534}}
{"_id":"1120778882028920834","created_at":1556049483,"lang":"es","retweeted_status":{"_id":"1120737825840873473","user":{"followers_count":10094,"friends_count":937,"id_str":"291002183","lang":"es","screen_name":"aprensasevilla","statuses_count":19919}},"text":"RT @aprensasevilla: Exigimos respeto al trabajo de los profesionales de la información #LibertadDePrensa https://t.co/uVNoOaZbkD","user":{"followers_count":992,"friends_count":777,"id_str":"285639869","lang":"es","screen_name":"pufabon","statuses_count":12739}}
{"_id":"1120779044973363201","created_at":1556049522,"lang":"und","retweeted_status":{"_id":"1120772595861860353","user":{"followers_count":602,"friends_count":1741,"id_str":"897533938045943809","lang":"es","screen_name":"Acatucitano80","statuses_count":47546}},"text":"RT @Acatucitano80: @JucilZaragoza @jusapol #EquiparacionYa\n#ELDEBATEenRTVE\n@jusapol\n@sanchezcastejon\n@PSOE\n@pablocasado_\n@populares\n@Pablo_…","user":{"followers_count":257,"friends_count":265,"id_str":"702891189","lang":"es","screen_name":"alaminos_javier","statuses_count":33984}}
{"_id":"1120779068998287367","created_at":1556049527,"lang":"es","retweeted_status":{"_id":"1120708475846365185","user":{"followers_count":3041,"friends_count":2561,"id_str":"3257024090","lang":"es","screen_name":"Iratxotravesa","statuses_count":19594}},"text":"RT @Iratxotravesa: No nos conformamos con lo menos malo de lo peor, con un partido que detrás del telón hace guiños a la derecha, pacta con…","user":{"followers_count":173,"friends_count":269,"id_str":"998627099924721664","lang":"es","screen_name":"Eugenie_eus_po","statuses_count":6029}}
{"_id":"1120779141362737161","created_at":1556049545,"lang":"es","retweeted_status":{"_id":"1120443056120111107","user":{"followers_count":2481,"friends_count":537,"id_str":"1120249086748385280","lang":"en","screen_name":"loscarnales_cat","statuses_count":184}},"text":"RT @loscarnales_cat: #Rusia| El diario ruso #Pravda entrevista a Quim Torra.\n\n■ Esta entrevista tendrá muchas críticas, sobre todo en Españ…","user":{"followers_count":2493,"friends_count":1159,"id_str":"169434390","lang":"ca","screen_name":"Guera1X","statuses_count":69055}}
{"_id":"1120779249235972097","created_at":1556049570,"lang":"es","retweeted_status":{"_id":"1120424534224535552","user":{"followers_count":2196,"friends_count":1908,"id_str":"924917322514599936","lang":"es","screen_name":"Encamtado1","statuses_count":6791}},"text":"RT @Encamtado1: Pongamos un ejemplo REAL de socialismo y comunismo..Andalucía..\n\n🗣 1 billón de € en ayudas europeas, la misma cantidad q en…","user":{"followers_count":465,"friends_count":242,"id_str":"911866325143818240","lang":"es","screen_name":"wos67","statuses_count":21223}}
{"_id":"1120779330110590976","created_at":1556049590,"lang":"ca","retweeted_status":{"_id":"1120654868191023106","user":{"followers_count":753211,"friends_count":4263,"id_str":"11611502","lang":"ca","screen_name":"KRLS","statuses_count":18656}},"text":"RT @KRLS: Alerta. És un compte que es fa passar pel CIS, utilitza la seva imatge i el seu nom... i no està suspès. Coses de @TwitterEspana,…","user":{"followers_count":669,"friends_count":1010,"id_str":"909061243582976000","lang":"es","screen_name":"groccanari2017","statuses_count":3463}}
{"_id":"1120779365875441664","created_at":1556049598,"lang":"es","text":"Eso sí, dentro del circo @Pablo_Iglesias_ demostró lo que es ; un político de pies a cabeza. No de esos de americana, corbata y gomina.","user":{"followers_count":246,"friends_count":513,"id_str":"365765989","lang":"es","screen_name":"aaronDG11","statuses_count":6698}}
{"_id":"1120779596012642305","created_at":1556049653,"lang":"es","retweeted_status":{"_id":"1120758618138259458","user":{"followers_count":185,"friends_count":51,"id_str":"924710694477553668","lang":"es","screen_name":"anmacot","statuses_count":1512}},"text":"RT @anmacot: @sanchezcastejon 30 AÑOS DE DESIGUALDAD ENTRE POLICÍAS.QUÉ VERGÜENZA. #EquiparacionYa\n#ElDebateDecisivo\n#ILPJusapol\n@jusapol\n@…","user":{"followers_count":602,"friends_count":1741,"id_str":"897533938045943809","lang":"es","screen_name":"Acatucitano80","statuses_count":47574}}
{"_id":"1120779687863771136","created_at":1556049675,"lang":"es","retweeted_status":{"_id":"1120775224570601477","user":{"followers_count":6212,"friends_count":4929,"id_str":"750032020093501440","lang":"es","screen_name":"RadioCarmena","statuses_count":16093}},"text":"RT @RadioCarmena: ¿Quién vive en un chalet de 600.000 euracos?\n#DebateAtresmedia https://t.co/ZKmF7N5k2N","user":{"followers_count":66,"friends_count":313,"id_str":"1553148888","lang":"es","screen_name":"SIncomodo","statuses_count":2875}}
{"_id":"1120779700861833216","created_at":1556049678,"lang":"es","retweeted_status":{"_id":"1120744404560510977","user":{"followers_count":1824,"friends_count":1708,"id_str":"987588684911382528","lang":"es","screen_name":"pepitongrillon","statuses_count":12669}},"text":"RT @pepitongrillon: Para el voto si que amáis a PN y GC gañanes.\n\nPrometer, prometer hasta meter y después nada de lo prometido.\n\n@jusapol…","user":{"followers_count":234,"friends_count":165,"id_str":"1018270136","lang":"es","screen_name":"jafricote","statuses_count":35512}}
{"_id":"1120779776166379520","created_at":1556049696,"lang":"es","text":"Que cosas","user":{"followers_count":48,"friends_count":291,"id_str":"2454953358","lang":"es","screen_name":"manuvalengar","statuses_count":14520}}
{"_id":"1120779823859761154","created_at":1556049707,"lang":"ca","retweeted_status":{"_id":"1120736753323790337","user":{"followers_count":8765,"friends_count":947,"id_str":"1932162895","lang":"ca","screen_name":"ReformaHoraria","statuses_count":23073}},"text":"RT @ReformaHoraria: Propostes eleccions #28A sobre ús del temps dels partits polítics\n #EleccionesGenerales #eleccions #DebateDecisivoARV @…","user":{"followers_count":286,"friends_count":1258,"id_str":"2262494336","lang":"ca","screen_name":"crisgonpi","statuses_count":5878}}
{"_id":"1120780023127056384","created_at":1556049755,"lang":"und","retweeted_status":{"_id":"1120779698274033666","user":{"followers_count":29,"friends_count":167,"id_str":"2340139264","lang":"es","screen_name":"cuchillodeferro","statuses_count":359}},"text":"RT @cuchillodeferro: @A3Noticias @atresmediacom @_anapastor_ @VicenteVallesTV @MomentsES #EquiparacionYa\n#ElDebateDecisivo\n#ILPJusapol\n@jus…","user":{"followers_count":61,"friends_count":48,"id_str":"887596261649600513","lang":"es","screen_name":"Carrrascoo","statuses_count":10905}}
{"_id":"1120780160582725634","created_at":1556049788,"lang":"es","retweeted_status":{"_id":"1120769771266629632","user":{"followers_count":237120,"friends_count":1011,"id_str":"2201623465","lang":"es","screen_name":"vox_es","statuses_count":35872}},"text":"RT @vox_es: 📹 Gran ovación a @Ortega_Smith en Las Rozas \n\n📣 \"Nos dijeron a los españoles que tendríamos un sistema democrático e íbamos a s…","user":{"followers_count":1907,"friends_count":2380,"id_str":"1018498437573115905","lang":"en","screen_name":"VerdadyVerdod","statuses_count":43967}}
{"_id":"1120780219948961794","created_at":1556049802,"lang":"und","retweeted_status":{"_id":"1120733926971117570","user":{"followers_count":248,"friends_count":208,"id_str":"935552882379841538","lang":"es","screen_name":"Maribel_Aviles_","statuses_count":17272}},"text":"RT @Maribel_Aviles_: @pablocasado_ @jujaeav #EquiparacionYA #ILPJusapol @JupolNacional \n@jucilnacional @AFAPOL_ \n@jusapol","user":{"followers_count":298,"friends_count":216,"id_str":"918502034596335616","lang":"es","screen_name":"JosAndr90869973","statuses_count":58807}}
{"_id":"1120780404158619648","created_at":1556049846,"lang":"es","text":"No veo maletines con atrezzo. Será posible un debate sin grafos, marcos y cacharrería variada? #ElDebateDecisivo","user":{"followers_count":21295,"friends_count":705,"id_str":"3511961","lang":"es","screen_name":"CesarCalderon","statuses_count":10701}}
{"_id":"1120780406457098240","created_at":1556049846,"lang":"es","retweeted_status":{"_id":"1120763943180480513","user":{"followers_count":204488,"friends_count":15963,"id_str":"499086428","lang":"es","screen_name":"DaniRemigio","statuses_count":1156}},"text":"RT @DaniRemigio: Pedro Sánchez llegando a el debate.\n\n#DebateAtresmedia\n#DebateA3Media\n#ElDebateDecisivo https://t.co/aQaGXNCY4O","user":{"followers_count":2285,"friends_count":1141,"id_str":"1330200259","lang":"en","screen_name":"LOCOCOMIO","statuses_count":163036}}
{"_id":"1120780452699213824","created_at":1556049857,"lang":"es","retweeted_status":{"_id":"1120763014095998977","user":{"followers_count":516,"friends_count":878,"id_str":"1099386286819954690","lang":"es","screen_name":"Cristin83590981","statuses_count":9529}},"text":"RT @Cristin83590981: 🔴Falta muy poco para que empiece #ElDebateDecisivo @sanchezcastejon. A partir de las 22:00 🕙 el segundo debate elector…","user":{"followers_count":137,"friends_count":180,"id_str":"2177075104","lang":"es","screen_name":"Puri65088032","statuses_count":11441}}
{"_id":"1120780559893114880","created_at":1556049883,"lang":"es","text":"QUE ALBERT RIVERA TRAE MAS COSAS  AY LAS CARTULINAAAAAS Y LAS FOTOS JAJAJAJAJAJAJA\n#ElDebateDecisivo","user":{"followers_count":45,"friends_count":80,"id_str":"1044610806","lang":"es","screen_name":"Aitor_HS","statuses_count":1642}}
{"_id":"1120780598371598342","created_at":1556049892,"lang":"es","text":"@cabezascrim me cuadra más con otra de las búsquedas más populares (¿cómo deshacerse de un cadáver?), aunque creo q… https://t.co/ssi9irkejm","user":{"followers_count":826,"friends_count":1402,"id_str":"247313295","lang":"es","screen_name":"jugunar","statuses_count":3239}}
{"_id":"1120780755083452416","created_at":1556049929,"lang":"und","retweeted_status":{"_id":"1120779528798969857","user":{"followers_count":62,"friends_count":58,"id_str":"915734276485902336","lang":"es","screen_name":"Juca55450372","statuses_count":5019}},"text":"RT @Juca55450372: @laSextaTV @_anapastor_ @VicenteVallesTV #EquiparacionYa\n#ElDebateDecisivo\n#ILPJusapol\n@jusapol\n@PSOE\n@populares\n@ahorapo…","user":{"followers_count":4083,"friends_count":3985,"id_str":"937444835681865730","lang":"es","screen_name":"Leonard24198","statuses_count":35910}}
{"_id":"1120780783906689031","created_at":1556049936,"lang":"es","retweeted_status":{"_id":"1120709791557533696","user":{"followers_count":3343,"friends_count":3751,"id_str":"762171630751801344","lang":"es","screen_name":"EnsaimadaMental","statuses_count":1145}},"text":"RT @EnsaimadaMental: Tu recibo de la luz por las nubes y sus exministros enchufados en las eléctricas. #HazQueNoPase https://t.co/eLaLofSO0c","user":{"followers_count":2324,"friends_count":1705,"id_str":"562932600","lang":"es","screen_name":"Olga_Hurtado66","statuses_count":169021}}
{"_id":"1120780820615237632","created_at":1556049945,"lang":"es","retweeted_status":{"_id":"1120601099889782784","user":{"followers_count":1396,"friends_count":1103,"id_str":"364595674","lang":"es","screen_name":"arturrr_","statuses_count":74301}},"text":"RT @arturrr_: Ciudadanos quiere darte una tarjeta con una bandera de España que sirve para exactamente lo mismo que la que ya tienes. Unida…","user":{"followers_count":819,"friends_count":708,"id_str":"964508058","lang":"es","screen_name":"veramarea","statuses_count":19587}}
{"_id":"1120780875925471232","created_at":1556049958,"lang":"es","text":"@marubimo Que poco demócratas donde esta VOX https://t.co/ciIgTI0rHQ","user":{"followers_count":343,"friends_count":345,"id_str":"2235459646","lang":"es","screen_name":"ARRAUTXES","statuses_count":35008}}
{"_id":"1120780969773027330","created_at":1556049980,"lang":"es","retweeted_status":{"_id":"1120585762926411782","user":{"followers_count":53995,"friends_count":4172,"id_str":"173541298","lang":"es","screen_name":"jordi_canyas","statuses_count":37635}},"text":"RT @jordi_canyas: Son insufriblemente pelmazos. No dejan milímetro sin manosear con su cansina, pesada y empalagosa tabarra amarilla. \nNi p…","user":{"followers_count":92,"friends_count":299,"id_str":"861130976","lang":"es","screen_name":"N3dVictor","statuses_count":4733}}
{"_id":"1120781033945935875","created_at":1556049996,"lang":"es","retweeted_status":{"_id":"1120451495365890049","user":{"followers_count":18930,"friends_count":862,"id_str":"12895152","lang":"es","screen_name":"elentirvigo","statuses_count":68198}},"text":"RT @elentirvigo: Miles gallegos abarrotan el acto de Vox de La Coruña para escuchar a Santiago Abascal. Podéis ver en esta entrada algunas…","user":{"followers_count":747,"friends_count":971,"id_str":"887452166826455040","lang":"es","screen_name":"TarnowskiPawel","statuses_count":333}}
{"_id":"1120781092288696321","created_at":1556050010,"lang":"es","retweeted_status":{"_id":"1120780119222706181","user":{"followers_count":834,"friends_count":510,"id_str":"304032557","lang":"es","screen_name":"hportales","statuses_count":2411}},"text":"RT @hportales: No puede ser que @Albert_Rivera tenga otra foto en el atril... #ElDebateDecisivo https://t.co/puYHT5im5y","user":{"followers_count":143,"friends_count":1259,"id_str":"102764416","lang":"es","screen_name":"Aidaa_PV","statuses_count":1139}}
{"_id":"1120781145585725442","created_at":1556050022,"lang":"es","retweeted_status":{"_id":"1120779225710120962","user":{"followers_count":15837,"friends_count":15746,"id_str":"866493324","lang":"es","screen_name":"aldocardinali","statuses_count":126948}},"text":"RT @aldocardinali: PC y UNASUR. PC llama a un amplio debate en la Cámara por retiro de Chile de UNASUR. ¿Afectará al PC y Otros, en las fue…","user":{"followers_count":4427,"friends_count":3183,"id_str":"1363109101","lang":"es","screen_name":"marceloalonsoh","statuses_count":180437}}
{"_id":"1120781168931233802","created_at":1556050028,"lang":"es","retweeted_status":{"_id":"1120770791010861058","user":{"followers_count":237137,"friends_count":1011,"id_str":"2201623465","lang":"es","screen_name":"vox_es","statuses_count":35872}},"text":"RT @vox_es: 📢🔴 El discurso de @Santi_ABASCAL en el gran acto de Las Rozas no se emitirá en directo. Estará disponible a partir de las 22:00…","user":{"followers_count":1318,"friends_count":855,"id_str":"2584572343","lang":"es","screen_name":"arlequin1403","statuses_count":55938}}
{"_id":"1120781210589040649","created_at":1556050038,"lang":"es","retweeted_status":{"_id":"1120430823612854272","user":{"followers_count":384,"friends_count":504,"id_str":"550426090","lang":"es","screen_name":"Kaleid173","statuses_count":39924}},"text":"RT @Kaleid173: Acabo de hacer un dibujo sobre el debate. #ELDEBATEenRTVE https://t.co/lh0IKtinwi","user":{"followers_count":58,"friends_count":121,"id_str":"982586386296590336","lang":"es","screen_name":"_Royi_","statuses_count":3746}}
{"_id":"1120781226351190017","created_at":1556050042,"lang":"es","retweeted_status":{"_id":"1120442468896526341","user":{"followers_count":963,"friends_count":1196,"id_str":"1628460614","lang":"es","screen_name":"Albertdw98","statuses_count":25736}},"text":"RT @Albertdw98: Te guste o no, este momento ha sido SU-BLI-ME. #ElDebateEnRTVE https://t.co/ERlYINuNqA","user":{"followers_count":1216,"friends_count":1117,"id_str":"519326785","lang":"es","screen_name":"tonigines","statuses_count":62833}}
{"_id":"1120781273067335680","created_at":1556050053,"lang":"es","text":"Que comience la guerra😂😂😂 \n#ElDebateDecisivo","user":{"followers_count":143,"friends_count":413,"id_str":"927704718","lang":"es","screen_name":"isabelaguadosg","statuses_count":460}}
{"_id":"1120781298145136641","created_at":1556050059,"lang":"es","text":"@Albert_Rivera donde están tus cartulinas weeiiii?","user":{"followers_count":47,"friends_count":124,"id_str":"919293382542979072","lang":"es","screen_name":"iriuw_","statuses_count":383}}
{"_id":"1120781355107987457","created_at":1556050072,"lang":"es","text":"Madre mía como está @Albert_Rivera espero que de verdad luego no pacte con el @PSOE de Pedrito #ElDebateDecisivo","user":{"followers_count":608,"friends_count":1008,"id_str":"250387855","lang":"es","screen_name":"NatRM_","statuses_count":3439}}
{"_id":"1120781382740008961","created_at":1556050079,"lang":"und","text":"#liquidarestepais #ElDebateDecisivo","user":{"followers_count":32,"friends_count":446,"id_str":"268422874","lang":"es","screen_name":"Vilarrube","statuses_count":185}}
{"_id":"1120781710969454592","created_at":1556050157,"lang":"es","text":"#DebateAtresmedia #DebateCTXT #ElDebateDecisivo \nTodos sabemos por qué estamos aquí... https://t.co/DkomzPEgqd","user":{"followers_count":2,"friends_count":101,"id_str":"1120257508566806528","lang":"es","screen_name":"SurrealCaptain","statuses_count":22}}
{"_id":"1120781769215705090","created_at":1556050171,"lang":"und","text":"@lasexta\n#EquiparacionYa\n#ElDebateDecisivo\n#ILPJusapol\n@jusapol\n@PSOE\n@populares\n@ahorapodemos\n@CiudadanosCs… https://t.co/HEJaqP35J2","user":{"followers_count":536,"friends_count":136,"id_str":"983464780265672704","lang":"es","screen_name":"JucilHuelva","statuses_count":732}}
{"_id":"1120781920999227392","created_at":1556050207,"lang":"es","text":"#ElDebateDecisivo Más falso que un billete de 15€. https://t.co/6eMTuLHRMI","user":{"followers_count":129,"friends_count":76,"id_str":"365363181","lang":"es","screen_name":"agranadosll","statuses_count":11100}}
{"_id":"1120782014926524416","created_at":1556050230,"lang":"es","retweeted_status":{"_id":"1120383916895088640","user":{"followers_count":12905,"friends_count":7900,"id_str":"339281879","lang":"es","screen_name":"elenay29","statuses_count":86412}},"text":"RT @elenay29: Dado que los taxistas proponen que no se vote ni al PP, ni a Cs ni a Vox yo desde aquí también propongo que no volvamos a cog…","user":{"followers_count":790,"friends_count":854,"id_str":"419923345","lang":"es","screen_name":"tipoduro2","statuses_count":8436}}
{"_id":"1120782056596885504","created_at":1556050240,"lang":"es","text":"Pinta bastante mejor que el anterior en cuanto a dinamismo televisivo e información para la ciudadanía.… https://t.co/1WYIARQ8zq","user":{"followers_count":354,"friends_count":445,"id_str":"305675842","lang":"es","screen_name":"MarinaSF_4","statuses_count":11373}}
{"_id":"1120782147575590913","created_at":1556050261,"lang":"es","retweeted_status":{"_id":"1120780916249513985","user":{"followers_count":8674,"friends_count":6745,"id_str":"1459779535","lang":"es","screen_name":"rafaruizmad","statuses_count":62486}},"text":"RT @rafaruizmad: #ElDebateDecisivo primeras palabras de Sánchez: no entra en mis planes pactar con Ciudadanos. Queda claro, no? Para tanto…","user":{"followers_count":697,"friends_count":143,"id_str":"2709928914","lang":"es","screen_name":"RosaPradasRegel","statuses_count":12058}}
{"_id":"1120782185211027456","created_at":1556050270,"lang":"es","retweeted_status":{"_id":"1120781731311828992","user":{"followers_count":57099,"friends_count":481,"id_str":"2841125981","lang":"es","screen_name":"MeroStation","statuses_count":30383}},"text":"RT @MeroStation: \"Hostia, que había que traer traje\" #ElDebateDecisivo https://t.co/6UOIquzDVY","user":{"followers_count":150,"friends_count":284,"id_str":"596871698","lang":"es","screen_name":"D8cerrato","statuses_count":6239}}
{"_id":"1120782229498662913","created_at":1556050281,"lang":"und","retweeted_status":{"_id":"1120403258424557568","user":{"followers_count":152,"friends_count":288,"id_str":"309383313","lang":"es","screen_name":"teonciyo","statuses_count":7014}},"text":"RT @teonciyo: #EquiparacionYa\n#ELDEBATEenRTVE\n@jusapol\n@sanchezcastejon\n@PSOE\n@pablocasado_\n@populares\n@Pablo_Iglesias_\n@ahorapodemos\n@Albe…","user":{"followers_count":103,"friends_count":47,"id_str":"1001042759866814464","lang":"en","screen_name":"sergio01781476","statuses_count":9739}}
{"_id":"1120782281151524864","created_at":1556050293,"lang":"es","retweeted_status":{"_id":"1120781211205550081","user":{"followers_count":29794,"friends_count":933,"id_str":"250193313","lang":"es","screen_name":"modesto_garcia","statuses_count":7902}},"text":"RT @modesto_garcia: Santiago Abascal fuera del plató pidiendo participar.\n\n#ElDebateDecisivo. https://t.co/HAXMT3qa7Z","user":{"followers_count":204,"friends_count":578,"id_str":"359535415","lang":"es","screen_name":"annagarciagaya","statuses_count":1822}}
{"_id":"1120782343403339777","created_at":1556050308,"lang":"es","retweeted_status":{"_id":"1120767863231524866","user":{"followers_count":603,"friends_count":544,"id_str":"99756299","lang":"es","screen_name":"RaquelSynyster","statuses_count":27223}},"text":"RT @RaquelSynyster: Era necesario y lo sabéis. \n\n#ElDebateEnRTVE https://t.co/1bW1D585zx","user":{"followers_count":673,"friends_count":680,"id_str":"2753308515","lang":"es","screen_name":"andreasanchb","statuses_count":17803}}
{"_id":"1120782349044678657","created_at":1556050309,"lang":"es","retweeted_status":{"_id":"1120774322472275971","user":{"followers_count":2680,"friends_count":3958,"id_str":"260715935","lang":"es","screen_name":"galaico44","statuses_count":5875}},"text":"RT @galaico44: Debate devaluado por la ausencia del futuro presidente de España #DebateAtresmedia https://t.co/O2XW02jUgI","user":{"followers_count":294,"friends_count":321,"id_str":"997580369154203649","lang":"es","screen_name":"ciberneando","statuses_count":1786}}
{"_id":"1120782356107943937","created_at":1556050311,"lang":"es","retweeted_status":{"_id":"1120770545082040322","user":{"followers_count":39124,"friends_count":1069,"id_str":"3299116330","lang":"es","screen_name":"EstefaniaJoaq","statuses_count":17558}},"text":"RT @EstefaniaJoaq: Javier Maroto (PP) dice que Pedro Sànchez ha ido arrastrado a los debates televisados. Pablo Casado no ha querido ser en…","user":{"followers_count":1693,"friends_count":2347,"id_str":"843951648","lang":"es","screen_name":"rafagallardo1","statuses_count":17685}}
{"_id":"1120782408599703552","created_at":1556050323,"lang":"es","retweeted_status":{"_id":"1120781731311828992","user":{"followers_count":57099,"friends_count":481,"id_str":"2841125981","lang":"es","screen_name":"MeroStation","statuses_count":30383}},"text":"RT @MeroStation: \"Hostia, que había que traer traje\" #ElDebateDecisivo https://t.co/6UOIquzDVY","user":{"followers_count":3246,"friends_count":659,"id_str":"244138821","lang":"es","screen_name":"RubenOwl","statuses_count":39168}}
{"_id":"1120782428644286464","created_at":1556050328,"lang":"es","retweeted_status":{"_id":"1120782192458764289","user":{"followers_count":6630,"friends_count":432,"id_str":"229861606","lang":"es","screen_name":"polinitito","statuses_count":125245}},"text":"RT @polinitito: Cuando habla Pablo Iglesias sólo puedo pensar en Fede imitándole. Es que le clava.","user":{"followers_count":312,"friends_count":357,"id_str":"255388496","lang":"es","screen_name":"capitanjavi","statuses_count":28549}}
{"_id":"1120782564535472130","created_at":1556050361,"lang":"und","retweeted_status":{"_id":"1120780404393414657","user":{"followers_count":124,"friends_count":66,"id_str":"1028689807382380544","lang":"es","screen_name":"UnkashP","statuses_count":3380}},"text":"RT @UnkashP: @jusapol @abc_es #EquiparacionYa\n#ElDebateDecisivo\n#ILPJusapol\n@jusapol\n@PSOE\n@populares\n@ahorapodemos\n@CiudadanosCs\n@vox_es\n@…","user":{"followers_count":114,"friends_count":8,"id_str":"887414281528102913","lang":"es","screen_name":"Bertran51838312","statuses_count":7923}}
{"_id":"1120782585926422530","created_at":1556050366,"lang":"es","retweeted_status":{"_id":"1120770545082040322","user":{"followers_count":39124,"friends_count":1069,"id_str":"3299116330","lang":"es","screen_name":"EstefaniaJoaq","statuses_count":17558}},"text":"RT @EstefaniaJoaq: Javier Maroto (PP) dice que Pedro Sànchez ha ido arrastrado a los debates televisados. Pablo Casado no ha querido ser en…","user":{"followers_count":122587,"friends_count":509,"id_str":"19292516","lang":"en","screen_name":"ramonlobo","statuses_count":35950}}
{"_id":"1120782596953317377","created_at":1556050368,"lang":"und","retweeted_status":{"_id":"1120753153052434437","user":{"followers_count":60,"friends_count":71,"id_str":"1063490508436250624","lang":"en","screen_name":"jupolcoslada","statuses_count":1494}},"text":"RT @jupolcoslada: @A3Noticias @atresmediacom @_anapastor_ @VicenteVallesTV @MomentsES #EquiparacionYa\n#ElDebateDecisivo\n#ILPJusapol\n@jusapo…","user":{"followers_count":65,"friends_count":32,"id_str":"4841742622","lang":"es","screen_name":"Carlhitos84","statuses_count":758}}
{"_id":"1120782621901033472","created_at":1556050374,"lang":"es","retweeted_status":{"_id":"1120782227913236486","user":{"followers_count":935063,"friends_count":5567,"id_str":"14436317","lang":"es","screen_name":"iescolar","statuses_count":75052}},"text":"RT @iescolar: Primera mentira de Casado. Dice que la inestabilidad política ha provocado \"más crisis económica\".\n\nLa economía, mientras tan…","user":{"followers_count":1249,"friends_count":247,"id_str":"1386526333","lang":"es","screen_name":"UlvicGH","statuses_count":11796}}
{"_id":"1120782655035969537","created_at":1556050382,"lang":"es","retweeted_status":{"_id":"1120774008809644033","user":{"followers_count":2298,"friends_count":1987,"id_str":"265418402","lang":"es","screen_name":"666olga","statuses_count":74654}},"text":"RT @666olga: Porque van PSOE, PP y C,s  vestidos igual? Que poquita personalidad tienen gran parte de nuestros políticos   🤔🤣🤣🤣🤦 #DebateAtr…","user":{"followers_count":693,"friends_count":716,"id_str":"788792161554800641","lang":"es","screen_name":"florecitazulita","statuses_count":26055}}
{"_id":"1120782729933721600","created_at":1556050400,"lang":"es","text":"La verdad Pablo Iglesias, se los come a todos en los debates.\n\n#ElDebateDecisivo","user":{"followers_count":156,"friends_count":216,"id_str":"1053228736651423745","lang":"es","screen_name":"Ladelbarrio12","statuses_count":2661}}
{"_id":"1120782730428669952","created_at":1556050400,"lang":"es","retweeted_status":{"_id":"1120782635389915136","user":{"followers_count":3,"friends_count":0,"id_str":"1120427550378008578","lang":"en","screen_name":"SandraManchola","statuses_count":31}},"text":"RT @SandraManchola: Que propuesta tienen para que las persianas de los autónomos desangrados y ahogados no se cierren ? https://t.co/A480x5…","user":{"followers_count":3,"friends_count":0,"id_str":"1120427550378008578","lang":"en","screen_name":"SandraManchola","statuses_count":32}}
{"_id":"1120782775286665224","created_at":1556050411,"lang":"es","text":"Participamos del debate en @DiputadosAR sobre el régimen de Responsabilidad Penal Juvenil para escuchar la posición… https://t.co/iDgCfXOBeQ","user":{"followers_count":332183,"friends_count":582,"id_str":"182925466","lang":"es","screen_name":"FilmusDaniel","statuses_count":28790}}
{"_id":"1120782781259427840","created_at":1556050412,"lang":"es","retweeted_status":{"_id":"1120378019187765248","user":{"followers_count":30640,"friends_count":1231,"id_str":"244101525","lang":"es","screen_name":"pmanglano","statuses_count":24719}},"text":"RT @pmanglano: En resumen, el PSOE ha arrasado Andalucía tras 40 años de gobierno, pero lo que necesita ahora España es otro gobierno del P…","user":{"followers_count":3027,"friends_count":3396,"id_str":"291030542","lang":"es","screen_name":"jhos_e","statuses_count":78048}}
{"_id":"1120782933508460547","created_at":1556050449,"lang":"es","retweeted_status":{"_id":"1120781563267043332","user":{"followers_count":89176,"friends_count":380,"id_str":"19163995","lang":"es","screen_name":"PabloMM","statuses_count":72231}},"text":"RT @PabloMM: Nuevo récord del mundo; Albert Rivera ha mencionado a \"los separatistas\", a Torra, a Rufián y a Puigdemont a los 3 segundos de…","user":{"followers_count":201,"friends_count":228,"id_str":"3264537088","lang":"es","screen_name":"rpalmodovar","statuses_count":14251}}
{"_id":"1120782966375047171","created_at":1556050456,"lang":"es","retweeted_status":{"_id":"1120782448613314560","user":{"followers_count":23,"friends_count":97,"id_str":"2775181048","lang":"es","screen_name":"AlcainusN","statuses_count":3459}},"text":"RT @AlcainusN: \"Nunca han gobernado tanto los indepes y los etarras\". Claro señor Casado, claro... #ElDebateDecisivo https://t.co/sCjHJbRior","user":{"followers_count":33,"friends_count":234,"id_str":"1136397396","lang":"es","screen_name":"j_ctorres","statuses_count":3709}}
{"_id":"1120783054551830528","created_at":1556050478,"lang":"es","retweeted_status":{"_id":"1120690492721770498","user":{"followers_count":935067,"friends_count":5567,"id_str":"14436317","lang":"es","screen_name":"iescolar","statuses_count":75053}},"text":"RT @iescolar: Ojo -&gt; El candidato de Vox a la alcaldía de Badajoz se presentó en 2007 y 2011 con el partido neonazi Democracia Nacional htt…","user":{"followers_count":244,"friends_count":465,"id_str":"894207585376710657","lang":"ca","screen_name":"MontseCasado3","statuses_count":11601}}
{"_id":"1120783087271645184","created_at":1556050485,"lang":"es","retweeted_status":{"_id":"1120780745683947525","user":{"followers_count":6771,"friends_count":997,"id_str":"707520514642808832","lang":"es","screen_name":"Mariagtriana","statuses_count":115098}},"text":"RT @Mariagtriana: ♦️Esperando El Minuto En El Debate Para Qué Pedro Diga , Qué Tiene Firmado \"El Pacto\".Una Imagen Vale Más Qué Mil Palabra…","user":{"followers_count":1940,"friends_count":2378,"id_str":"1100506955381129216","lang":"es","screen_name":"NeptuniaVox","statuses_count":5004}}
{"_id":"1120783233841553415","created_at":1556050520,"lang":"es","retweeted_status":{"_id":"1120641831866445825","user":{"followers_count":1338,"friends_count":1364,"id_str":"1051863640675155968","lang":"es","screen_name":"Pitu_Caleya","statuses_count":1766}},"text":"RT @Pitu_Caleya: Dejar las DROGAS xfavor, gente del @PACMA.... https://t.co/EMYWCawg9K","user":{"followers_count":356,"friends_count":588,"id_str":"513285708","lang":"es","screen_name":"astrisc0","statuses_count":36053}}
{"_id":"1120783248727183362","created_at":1556050524,"lang":"es","retweeted_status":{"_id":"1120783212891058176","user":{"followers_count":35268,"friends_count":38419,"id_str":"1577384395","lang":"es","screen_name":"7Josean7","statuses_count":220927}},"text":"RT @7Josean7: Por el momento muy bien lxs periodistas yendo a las contradicciones del PP, de Cs y del PsoE. #ElDebateDecisivo https://t.co/…","user":{"followers_count":35268,"friends_count":38419,"id_str":"1577384395","lang":"es","screen_name":"7Josean7","statuses_count":220928}}
{"_id":"1120783280331214848","created_at":1556050531,"lang":"es","retweeted_status":{"_id":"1120780476577349633","user":{"followers_count":37734,"friends_count":25837,"id_str":"216328136","lang":"es","screen_name":"cmgorriaran","statuses_count":199785}},"text":"RT @cmgorriaran: Por qué llaman \"debate\" a un espectáculo rígido donde están pactados participantes y excluidos, temas presentes y ausentes…","user":{"followers_count":1525,"friends_count":1271,"id_str":"344715663","lang":"es","screen_name":"caparrones","statuses_count":151395}}
{"_id":"1120783384190554112","created_at":1556050556,"lang":"es","retweeted_status":{"_id":"1120422088634982400","user":{"followers_count":116275,"friends_count":80890,"id_str":"2301878362","lang":"es","screen_name":"vmm7773","statuses_count":61408}},"text":"RT @vmm7773: Pablo Casado dice que cuando gobierna el PP España es un país líder en todo.\n\nSupongo que se refiere a ... Líder en corrupción…","user":{"followers_count":866,"friends_count":2017,"id_str":"932414195613814787","lang":"es","screen_name":"Mayka41328150","statuses_count":5761}}
{"_id":"1120783394005311488","created_at":1556050558,"lang":"es","retweeted_status":{"_id":"1120562981811707905","user":{"followers_count":1882,"friends_count":1583,"id_str":"2714378434","lang":"es","screen_name":"MarisaVaron","statuses_count":18755}},"text":"RT @MarisaVaron: @sanchezcastejon Por una vez en la vida, y que no sirva como precedente, te voy a hacer caso, el #28A #PorEspaña #YoVotoVox","user":{"followers_count":3890,"friends_count":4313,"id_str":"1012254926687350785","lang":"en","screen_name":"Trix8Pat","statuses_count":56248}}
{"_id":"1120783426662092801","created_at":1556050566,"lang":"es","retweeted_status":{"_id":"1120778312891150336","user":{"followers_count":334091,"friends_count":1,"id_str":"952129529782337536","lang":"es","screen_name":"LaResistencia","statuses_count":11240}},"text":"RT @LaResistencia: ¿Tenéis ya la heroína y el pañal para ver el debate?","user":{"followers_count":436,"friends_count":397,"id_str":"1352571218","lang":"es","screen_name":"ainhoacortesper","statuses_count":2350}}
{"_id":"1120783457351798785","created_at":1556050574,"lang":"es","retweeted_status":{"_id":"1120782768118616065","user":{"followers_count":1130,"friends_count":5001,"id_str":"1097801042660601856","lang":"es","screen_name":"pablomangxs","statuses_count":381}},"text":"RT @pablomangxs: Twitter esperando a que Albert Rivera abra el bolsillo mágico... #ElDebateDecisivo https://t.co/MeQQn7l30R","user":{"followers_count":5495,"friends_count":284,"id_str":"223647359","lang":"es","screen_name":"FlyingRegrets","statuses_count":203397}}
{"_id":"1120783467682455559","created_at":1556050576,"lang":"es","retweeted_status":{"_id":"1120424914677370885","user":{"followers_count":2418,"friends_count":315,"id_str":"720831466","lang":"es","screen_name":"FortuneArturo","statuses_count":8617}},"text":"RT @FortuneArturo: ¡QUE ALGUIEN LE PREGUNTE A SÁNCHEZ SI VA A INDULTAR A DIEGO COSTA!\n#ELDEBATEenRTVE","user":{"followers_count":22,"friends_count":202,"id_str":"927119873989373952","lang":"es","screen_name":"DCovatillas","statuses_count":1445}}
{"_id":"1120783556945559557","created_at":1556050597,"lang":"es","retweeted_status":{"_id":"1120655867395833856","user":{"followers_count":39978,"friends_count":1242,"id_str":"4119160593","lang":"es","screen_name":"Julio_Rodr_","statuses_count":3130}},"text":"RT @Julio_Rodr_: Art. 50. Los poderes públicos garantizarán, mediante pensiones adecuadas y periódicamente actualizadas, la suficiencia eco…","user":{"followers_count":952,"friends_count":1455,"id_str":"888446063719395328","lang":"es","screen_name":"EmilioAgustnGa1","statuses_count":8085}}
{"_id":"1120783599991754752","created_at":1556050608,"lang":"es","text":"AVISO URGENTE: El debate bueno está a punto de empezar en @GanbaraEiTB.","user":{"followers_count":7876,"friends_count":1104,"id_str":"392665038","lang":"es","screen_name":"gara_iiriondo","statuses_count":25690}}
{"_id":"1120783613954600960","created_at":1556050611,"lang":"es","text":"“Aquí el más mentiroso es el señor Sánchez” Pablo Casado (él no niega serlo entonces). #ElDebateDecisivo","user":{"followers_count":499,"friends_count":454,"id_str":"1924666136","lang":"es","screen_name":"daocal","statuses_count":18643}}
{"_id":"1120783629842550784","created_at":1556050615,"lang":"es","retweeted_status":{"_id":"1120781847036821505","user":{"followers_count":4724,"friends_count":1033,"id_str":"237466725","lang":"es","screen_name":"jalemanuris","statuses_count":1916}},"text":"RT @jalemanuris: Casado efectivamente abre los primeros ataques contra Ciudadanos. Le culpa de fragmentar a la derecha y le recuerda el pac…","user":{"followers_count":2809,"friends_count":2545,"id_str":"274664446","lang":"es","screen_name":"sfp_1975","statuses_count":305732}}
{"_id":"1120783676982296577","created_at":1556050626,"lang":"es","retweeted_status":{"_id":"1120782690041638912","user":{"followers_count":60,"friends_count":190,"id_str":"735926412411031553","lang":"es","screen_name":"AliciaDomnech4","statuses_count":334}},"text":"RT @AliciaDomnech4: Nos tienen ahogados, somos su hucha, nos tenemos que hacer oir.\nDeben tenernos en cuenta, somos muchos.\n #ElDebateDecis…","user":{"followers_count":69,"friends_count":352,"id_str":"796437075893616641","lang":"es","screen_name":"mariaje69","statuses_count":1094}}
{"_id":"1120783732468781056","created_at":1556050639,"lang":"es","text":"Puede Albert Rivera sacar el marco otra vez","user":{"followers_count":2659,"friends_count":880,"id_str":"1643095826","lang":"es","screen_name":"juustbeelieve","statuses_count":96823}}
{"_id":"1120783772356620291","created_at":1556050649,"lang":"es","text":"Tiene la tesis Rivera tiene la tesis!!!! #eldebatedecisivo","user":{"followers_count":91,"friends_count":376,"id_str":"149214409","lang":"es","screen_name":"AlejoGracia","statuses_count":5974}}
{"_id":"1120784089794187267","created_at":1556050724,"lang":"es","text":"Oye, muy bien Iglesias #ElDebateDecisivo","user":{"followers_count":695,"friends_count":337,"id_str":"2620703981","lang":"es","screen_name":"sandrafm01","statuses_count":28485}}
{"_id":"1120784165790736386","created_at":1556050742,"lang":"es","text":"Pablo...te repites, que este debate es otro...no el de ayer.","user":{"followers_count":8,"friends_count":95,"id_str":"1034778175589543938","lang":"es","screen_name":"capitan134","statuses_count":1826}}
{"_id":"1120784247512551424","created_at":1556050762,"lang":"es","text":"Ya salió Venezuela, chupito #ElDebateDecisivo #LaHistoriaLaEscribesTú #28A #UnidasPodemos","user":{"followers_count":690,"friends_count":1293,"id_str":"166146178","lang":"es","screen_name":"noelgz7","statuses_count":8171}}
{"_id":"1120784325849624577","created_at":1556050781,"lang":"es","text":"\"Y tú qué eres, el árbitro?\" \n~Don Albert Rivera~ 2019.","user":{"followers_count":238,"friends_count":326,"id_str":"970443667","lang":"es","screen_name":"jaimeboukhrij","statuses_count":631}}
{"_id":"1120784387455574016","created_at":1556050795,"lang":"es","text":"SU TESIS JAJAJAJAJA\n\n#ElDebateDecisivo","user":{"followers_count":516,"friends_count":428,"id_str":"439443524","lang":"es","screen_name":"revert_maria","statuses_count":3398}}
{"_id":"1120784403481886722","created_at":1556050799,"lang":"es","text":"Madre de Dios la que se acaba de liar en un puto segundo \n#ElDebateDecisivo","user":{"followers_count":431,"friends_count":167,"id_str":"2206035585","lang":"es","screen_name":"manu_daur","statuses_count":11893}}
{"_id":"1120784481714147334","created_at":1556050818,"lang":"es","retweeted_status":{"_id":"1120601099889782784","user":{"followers_count":1398,"friends_count":1103,"id_str":"364595674","lang":"es","screen_name":"arturrr_","statuses_count":74308}},"text":"RT @arturrr_: Ciudadanos quiere darte una tarjeta con una bandera de España que sirve para exactamente lo mismo que la que ya tienes. Unida…","user":{"followers_count":380,"friends_count":540,"id_str":"634804826","lang":"es","screen_name":"DavidBoubeta","statuses_count":25353}}
{"_id":"1120784562026627073","created_at":1556050837,"lang":"es","retweeted_status":{"_id":"1120783730010939395","user":{"followers_count":10202,"friends_count":2035,"id_str":"2819381883","lang":"es","screen_name":"rouco64","statuses_count":71848}},"text":"RT @rouco64: 🛑🛑Torra al que Sánchez llamó Le Pen, ahora es colega y necesita sus votos es falso dice Sánchez 😂😂🔻🔻🔻 #28A #ElDebateDecisivo h…","user":{"followers_count":474,"friends_count":1203,"id_str":"1001537214","lang":"es","screen_name":"educodi1educodi","statuses_count":13449}}
{"_id":"1120784590854131713","created_at":1556050844,"lang":"es","retweeted_status":{"_id":"1120784424948457472","user":{"followers_count":443576,"friends_count":1304,"id_str":"11419202","lang":"es","screen_name":"dbravo","statuses_count":17856}},"text":"RT @dbravo: A Albert Rivera le han dicho que gana el que más memes genere","user":{"followers_count":588,"friends_count":139,"id_str":"253643132","lang":"en-gb","screen_name":"israel_p_s","statuses_count":5335}}
{"_id":"1120784594834481155","created_at":1556050845,"lang":"es","retweeted_status":{"_id":"1120782768118616065","user":{"followers_count":1131,"friends_count":5001,"id_str":"1097801042660601856","lang":"es","screen_name":"pablomangxs","statuses_count":383}},"text":"RT @pablomangxs: Twitter esperando a que Albert Rivera abra el bolsillo mágico... #ElDebateDecisivo https://t.co/MeQQn7l30R","user":{"followers_count":18,"friends_count":58,"id_str":"950388266074890240","lang":"es","screen_name":"maricarmengarg","statuses_count":119}}
